roimarker/__init__.py
roimarker/__main__.py
roimarker/arrow_selector.py
roimarker/marker.py
roimarker/version.py
roimarker-0.2.1.dist-info/LICENSE
roimarker-0.2.1.dist-info/METADATA
roimarker-0.2.1.dist-info/WHEEL
roimarker-0.2.1.dist-info/top_level.txt
roimarker-0.2.1.dist-info/RECORD
