Metadata-Version: 2.1
Name: roimarker
Version: 0.2.1
Summary: A rectangle-ROI annotator using matplotlib
Home-page: https://github.com/jkemppainen/roimarker
Author: Joni Kemppainen
Author-email: joni.kemppainen@windowslive.com
Classifier: Programming Language :: Python :: 3
Classifier: License :: OSI Approved :: GNU General Public License v3 (GPLv3) 
Classifier: Operating System :: OS Independent
Requires-Python: >=3.0
License-File: LICENSE
Requires-Dist: numpy
Requires-Dist: tifffile
Requires-Dist: matplotlib
